typedboto3/__init__.py
typedboto3/cognito/__init__.py
typedboto3/cognito/cognito_client.py
typedboto3/cognito/cognito_enum.py
typedboto3/cognito/common/__init__.py
typedboto3/cognito/common/analytics_metadata.py
typedboto3/cognito/common/code_delivery_details.py
typedboto3/cognito/common/context_data.py
typedboto3/cognito/common/device_metadata.py
typedboto3/cognito/common/user_attribute.py
typedboto3/cognito/common/user_context_data.py
typedboto3/cognito/request/__init__.py
typedboto3/cognito/request/admin_initiate_auth_request.py
typedboto3/cognito/request/admin_update_user_attributes_request.py
typedboto3/cognito/request/change_password_request.py
typedboto3/cognito/request/confirm_forgot_password_request.py
typedboto3/cognito/request/confirm_sign_up_request.py
typedboto3/cognito/request/forgot_password_request.py
typedboto3/cognito/request/initiate_auth_request.py
typedboto3/cognito/request/resend_confirmation_code_request.py
typedboto3/cognito/request/reset_password_request.py
typedboto3/cognito/request/revoke_token_request.py
typedboto3/cognito/request/sign_up_request.py
typedboto3/cognito/response/__init__.py
typedboto3/cognito/response/admin_initiate_auth_response.py
typedboto3/cognito/response/forgot_password_response.py
typedboto3/cognito/response/get_cognito_user_response.py
typedboto3/cognito/response/initiate_auth_response.py
typedboto3/cognito/response/resend_confirmation_code_response.py
typedboto3/cognito/response/sign_up_response.py
typedboto3/util/__init__.py
typedboto3/util/convert.py
typed_boto3-0.2.dist-info/LICENCE.txt
typed_boto3-0.2.dist-info/METADATA
typed_boto3-0.2.dist-info/WHEEL
typed_boto3-0.2.dist-info/top_level.txt
typed_boto3-0.2.dist-info/RECORD
